Doc/__init__.py
MetricTools/C_visitor.py
MetricTools/Cyclomatic.py
MetricTools/File_visit.py
MetricTools/Java_visitor.py
MetricTools/Parallel_cyclomatic.py
MetricTools/PyCyclomatic.py
MetricTools/__init__.py
MetricTools/test_C_visitor.py
MetricTools/test_Cyclomatic.py
MetricTools/test_File_visit.py
MetricTools/test_Java_visitor.py
MetricTools/test_Parallel_cyclomatic.py
MetricTools/test_PyCyclomatic.py
MetricTools/test/__init__.py
MetricTools/test/file_visit_test.txt
MetricTools/test/test.c
MetricTools/test/test.java
MetricTools/vendor/__init__.py
MetricTools/vendor/tree-sitter-c/.appveyor.yml
MetricTools/vendor/tree-sitter-c/.gitattributes
MetricTools/vendor/tree-sitter-c/.gitignore
MetricTools/vendor/tree-sitter-c/.npmignore
MetricTools/vendor/tree-sitter-c/.travis.yml
MetricTools/vendor/tree-sitter-c/Cargo.toml
MetricTools/vendor/tree-sitter-c/LICENSE
MetricTools/vendor/tree-sitter-c/README.md
MetricTools/vendor/tree-sitter-c/binding.gyp
MetricTools/vendor/tree-sitter-c/grammar.js
MetricTools/vendor/tree-sitter-c/package.json
MetricTools/vendor/tree-sitter-c/bindings/node/binding.cc
MetricTools/vendor/tree-sitter-c/bindings/node/index.js
MetricTools/vendor/tree-sitter-c/bindings/rust/README.md
MetricTools/vendor/tree-sitter-c/bindings/rust/build.rs
MetricTools/vendor/tree-sitter-c/bindings/rust/lib.rs
MetricTools/vendor/tree-sitter-c/examples/cluster.c
MetricTools/vendor/tree-sitter-c/examples/malloc.c
MetricTools/vendor/tree-sitter-c/examples/parser.c
MetricTools/vendor/tree-sitter-c/queries/highlights.scm
MetricTools/vendor/tree-sitter-c/src/grammar.json
MetricTools/vendor/tree-sitter-c/src/node-types.json
MetricTools/vendor/tree-sitter-c/src/parser.c
MetricTools/vendor/tree-sitter-c/src/tree_sitter/parser.h
MetricTools/vendor/tree-sitter-c/test/corpus/ambiguities.txt
MetricTools/vendor/tree-sitter-c/test/corpus/crlf.txt
MetricTools/vendor/tree-sitter-c/test/corpus/declarations.txt
MetricTools/vendor/tree-sitter-c/test/corpus/expressions.txt
MetricTool-0.1.5.dist-info/METADATA
MetricTool-0.1.5.dist-info/WHEEL
MetricTool-0.1.5.dist-info/top_level.txt
MetricTool-0.1.5.dist-info/RECORD
