Metadata-Version: 2.1
Name: MetricTool
Version: 0.1.5
Summary: 针对多种不同源码语言的度量分析工具。
Home-page: https://gitee.com/imlaji/cyclomatic-complexity/tree/master
Author: bobo.yang
Author-email: ybb_y1b1b1@163.com
Maintainer: boboyang
Maintainer-email: ybb_y1b1b1@163.com
License: BSD License
Platform: all
Classifier: Programming Language :: Python :: 3
Classifier: License :: OSI Approved :: MIT License
Classifier: Operating System :: OS Independent
Requires-Python: >=3.4
Requires-Dist: tree-sitter (>=0.19.0)
